merchise.lint-0.17-py3.6-nspkg.pth
merchise/lint/__init__.py
merchise/lint/engine.py
merchise/lint/main.py
merchise/lint/checkers/__init__.py
merchise/lint/checkers/absolute_import_check.py
merchise/lint/checkers/break_or_cont.py
merchise/lint/checkers/mock_check.py
merchise/lint/checkers/odoo_i18n.py
merchise/lint/checkers/pdb_check.py
merchise/lint/eslint/jsx-needs-il8n.js
merchise.lint-0.17.dist-info/METADATA
merchise.lint-0.17.dist-info/WHEEL
merchise.lint-0.17.dist-info/entry_points.txt
merchise.lint-0.17.dist-info/namespace_packages.txt
merchise.lint-0.17.dist-info/top_level.txt
merchise.lint-0.17.dist-info/RECORD
