Metadata-Version: 2.1
Name: merchise.lint
Version: 0.17
Summary: Merchise Lint Checks (for CI)
Home-page: http://www.merchise.org/
Author: Merchise Autrement
Author-email: info@merchise.org
License: GPL
Platform: UNKNOWN
Classifier: Programming Language :: Python
Requires-Dist: flake8 (<4,>=3.8)
Requires-Dist: pycodestyle
Requires-Dist: glob2 (>=0.4.1)
